CHANGES.md
MANIFEST.in
README.md
UNLICENSE
setup.py
src/pyramid_weblayer/__init__.py
src/pyramid_weblayer/campaign.py
src/pyramid_weblayer/csrf.py
src/pyramid_weblayer/flash.py
src/pyramid_weblayer/flat.py
src/pyramid_weblayer/hsts.py
src/pyramid_weblayer/humanize.py
src/pyramid_weblayer/i18n.py
src/pyramid_weblayer/layout.py
src/pyramid_weblayer/main.py
src/pyramid_weblayer/markdown.py
src/pyramid_weblayer/nav.py
src/pyramid_weblayer/patch.py
src/pyramid_weblayer/queue.py
src/pyramid_weblayer/redirect.py
src/pyramid_weblayer/seen.py
src/pyramid_weblayer/serve.py
src/pyramid_weblayer/session.py
src/pyramid_weblayer/snip.py
src/pyramid_weblayer/track.py
src/pyramid_weblayer/tx.py
src/pyramid_weblayer/utils.py
src/pyramid_weblayer/views.py
src/pyramid_weblayer.egg-info/PKG-INFO
src/pyramid_weblayer.egg-info/SOURCES.txt
src/pyramid_weblayer.egg-info/dependency_links.txt
src/pyramid_weblayer.egg-info/not-zip-safe
src/pyramid_weblayer.egg-info/requires.txt
src/pyramid_weblayer.egg-info/top_level.txt
src/pyramid_weblayer/templates/csrf_ajax_setup.mako
src/pyramid_weblayer/templates/form.mako
src/pyramid_weblayer/tests/__init__.py
src/pyramid_weblayer/tests/test_csrf.py
src/pyramid_weblayer/tests/test_i18n.mako
src/pyramid_weblayer/tests/test_integration.py